[{
  "id": 1,
  "name": "Pear",
  "seat": 1,
  "price": "$47.29",
  "img": "http://dummyimage.com/155x180.png/dddddd/000000"
}, {
  "id": 2,
  "name": "Quinapril",
  "seat": 2,
  "price": "$81.83",
  "img": "http://dummyimage.com/200x244.png/cc0000/ffffff"
}, {
  "id": 3,
  "name": "HYDROXYZINE HYDROCHLORIDE",
  "seat": 3,
  "price": "$69.29",
  "img": "http://dummyimage.com/245x138.png/dddddd/000000"
}, {
  "id": 4,
  "name": "Meloxicam",
  "seat": 4,
  "price": "$16.74",
  "img": "http://dummyimage.com/195x126.png/5fa2dd/ffffff"
}, {
  "id": 5,
  "name": "Amlodipine Besylate and Benazepril Hydrochloride",
  "seat": 5,
  "price": "$26.01",
  "img": "http://dummyimage.com/238x222.png/ff4444/ffffff"
}, {
  "id": 6,
  "name": "Oxygen",
  "seat": 6,
  "price": "$29.89",
  "img": "http://dummyimage.com/239x226.png/5fa2dd/ffffff"
}, {
  "id": 7,
  "name": "Alprazolam",
  "seat": 7,
  "price": "$33.50",
  "img": "http://dummyimage.com/231x160.png/dddddd/000000"
}, {
  "id": 8,
  "name": "DR. RECKEWEG R76 Herbamine Forte",
  "seat": 8,
  "price": "$70.93",
  "img": "http://dummyimage.com/131x113.png/ff4444/ffffff"
}, {
  "id": 9,
  "name": "Doxazosin",
  "seat": 9,
  "price": "$36.36",
  "img": "http://dummyimage.com/136x144.png/dddddd/000000"
}, {
  "id": 10,
  "name": "Terazosin Hydrochloride",
  "seat": 10,
  "price": "$44.23",
  "img": "http://dummyimage.com/235x160.png/5fa2dd/ffffff"
}, {
  "id": 11,
  "name": "BENZOYL PEROXIDE",
  "seat": 11,
  "price": "$88.46",
  "img": "http://dummyimage.com/246x131.png/ff4444/ffffff"
}, {
  "id": 12,
  "name": "CYBERWHITE HD UV PROTECTOR BROAD SPECTRUM SPF 50",
  "seat": 12,
  "price": "$19.47",
  "img": "http://dummyimage.com/239x195.png/5fa2dd/ffffff"
}]